LICENSE
MANIFEST.in
README.md
changelog.md
pyproject.toml
setup.py
.circleci/config.yml
cuda_complex/LICENSE.txt
cuda_complex/README.txt
cuda_complex/cuda_complex.hpp
doc/Makefile
doc/source/conf.py
doc/source/index.rst
fsph/__init__.py
fsph/_fsph.cpp
fsph/_fsph.pyx
fsph/cpp.pxd
fsph/tf_ops.py
fsph/version.py
fsph.egg-info/PKG-INFO
fsph.egg-info/SOURCES.txt
fsph.egg-info/dependency_links.txt
fsph.egg-info/requires.txt
fsph.egg-info/top_level.txt
src/SharedArray.hpp
src/internal.hpp
src/spherical_harmonics.hpp
src/tensorflow_op.cpp
src/tensorflow_op_gpu.cpp
src/tensorflow_op_gpu.cu
src/tensorflow_op_gpu.cu.hpp
tests/benchmark_scipy.py
tests/benchmark_tf.py
tests/test_boost.cpp
tests/test_scipy.py
tests/test_tensorflow.py