Metadata-Version: 2.1
Name: fsph
Version: 0.3.0
Summary: Fast sequential spherical harmonics calculation
Home-page: http://fsph.readthedocs.io
Author: Matthew Spellings
Author-email: mspells@umich.edu
License: UNKNOWN
Project-URL: Documentation, http://fsph.readthedocs.io/
Project-URL: Source, https://github.com/glotzerlab/fsph
Platform: UNKNOWN
Classifier: Development Status :: 5 - Production/Stable
Classifier: License :: OSI Approved :: MIT License
Classifier: Programming Language :: Python :: 2
Classifier: Programming Language :: Python :: 3
Classifier: Topic :: Scientific/Engineering :: Mathematics
Provides-Extra: tensorflow
License-File: LICENSE
